Notebooks/__init__.py
analysis/__init__.py
analysis/analysis_utils.py
analysis/behavior_utils.py
analysis/cellreg_utils.py
analysis/clustering.py
analysis/cnmfe_utils.py
analysis/dlc_utils.py
analysis/fc_box.py
analysis/graph_analysis_utils.py
analysis/object_tests.py
analysis/place_cell_analysis.py
analysis/resampling.py
analysis/roi_analysis.py
analysis/roi_tools.py
analysis/sig_proc.py
analysis/time_in_rois.py
analysis/visualize.py
analysis/y_maze_analisys.py
gui/__init__.py
gui/client.py
gui/data_dialogs.py
gui/main.py
gui/mini_player.py
gui/neuron_overlay.py
gui/pyqt_wrapper.py
gui/server.py
gui/vlc.py
jb_caliban-0.0.16.dist-info/LICENSE
jb_caliban-0.0.16.dist-info/METADATA
jb_caliban-0.0.16.dist-info/WHEEL
jb_caliban-0.0.16.dist-info/top_level.txt
jb_caliban-0.0.16.dist-info/RECORD
