Metadata-Version: 2.1
Name: jb-caliban
Version: 0.0.16
Summary: Calcium Imaging and Behavior Analysis
Home-page: https://github.com/jaberry/caliban
Author: Jack Berry, Gergely Turi
Author-email: gt22553@cumc.columbia.edu
License: UNKNOWN
Project-URL: Bug Tracker, https://github.com/jaberry/caliban/issues
Platform: UNKNOWN
Classifier: Development Status :: 3 - Alpha
Classifier: Programming Language :: Python :: 3.7
Classifier: License :: OSI Approved :: GNU General Public License v3 (GPLv3)
Classifier: Operating System :: OS Independent
Requires-Python: >=3.7
License-File: LICENSE
Requires-Dist: cython
Requires-Dist: networkx
Requires-Dist: numpy
Requires-Dist: pandas
Requires-Dist: scikit-learn
Requires-Dist: seaborn
Requires-Dist: h5py
Requires-Dist: holoviews
Requires-Dist: shapely
Requires-Dist: statsmodels
Requires-Dist: opencv-python
Requires-Dist: bokeh
